.gitignore
LICENSE
MANIFEST.in
README.rst
setup.py
txbugzilla/__init__.py
txbugzilla/proxy.py
txbugzilla.egg-info/PKG-INFO
txbugzilla.egg-info/SOURCES.txt
txbugzilla.egg-info/dependency_links.txt
txbugzilla.egg-info/not-zip-safe
txbugzilla.egg-info/requires.txt
txbugzilla.egg-info/top_level.txt
txbugzilla/tests/test_connect.py
txbugzilla/tests/test_find_by_external_tracker.py