Metadata-Version: 1.1
Name: txbugzilla
Version: 2.1.0
Summary: Twisted API for Bugzilla
Home-page: https://github.com/ktdreyer/txbugzilla
Author: Ken Dreyer
Author-email: ktdreyer@ktdreyer.com
License: MIT
Keywords: bugzilla,twisted
Platform: UNKNOWN
Classifier: Development Status :: 5 - Production/Stable
Classifier: Framework :: Twisted
Classifier: Intended Audience :: Developers
Classifier: License :: OSI Approved :: MIT License
Classifier: Topic :: Software Development :: Bug Tracking
Classifier: Operating System :: OS Independent
Classifier: Programming Language :: Python :: 2.7
Classifier: Programming Language :: Python :: 3.5
Classifier: Programming Language :: Python :: 3.6
License-File: LICENSE
